<?xml version="1.0" encoding="UTF-8" standalone="yes" ?>
<database name="HardCore Web Content Management">
 <table name="content">
  <row>
   <column name="id" value="6639" />
   <column name="locked" value="0" />
   <column name="created" value="2004-06-18 01:02:23" />
   <column name="updated" value="2004-06-19 16:55:23" />
   <column name="published" value="2004-06-19 16:55:23" />
   <column name="scheduled_publish" value="" />
   <column name="scheduled_unpublish" value="" />
   <column name="status" value="" />
   <column name="created_by" value="admin" />
   <column name="updated_by" value="admin" />
   <column name="published_by" value="admin" />
   <column name="revision" value="" />
   <column name="version" value="" />
   <column name="version_master" value="0" />
   <column name="title" value="User Registration Form" />
   <column name="author" value="" />
   <column name="keywords" value="" />
   <column name="description" value="" />
   <column name="htmlheader" value="" />
   <column name="htmlbodyonload" value="" />
   <column name="url" value="" />
   <column name="content" value="&lt;div class=&quot;box&quot;&gt;
&lt;h2&gt;&amp;nbsp;&lt;/h2&gt;
&lt;h2&gt;Sign Up For User Account&lt;br&gt;
&lt;/h2&gt;
&lt;p&gt;&amp;nbsp;&lt;/p&gt;
&lt;p&gt;&lt;font color=&quot;red&quot;&gt;&lt;b&gt;@@@error@@@&lt;/b&gt;&lt;/font&gt;&lt;/p&gt;
&lt;form action=&quot;/register.php?id=@@@id@@@&quot; method=&quot;post&quot;&gt;
&lt;input name=&quot;user_id&quot; value=&quot;573&quot; type=&quot;hidden&quot;&gt;
&lt;input name=&quot;content_id&quot; value=&quot;6640&quot; type=&quot;hidden&quot;&gt;
&lt;input name=&quot;publish&quot; value=&quot;yes&quot; type=&quot;hidden&quot;&gt;
&lt;input name=&quot;redirect&quot; value=&quot;/page.php?id=6641&quot; type=&quot;hidden&quot;&gt;
&lt;table align=&quot;center&quot; border=&quot;0&quot; cellpadding=&quot;0&quot; cellspacing=&quot;0&quot; width=&quot;400&quot;&gt;
&lt;tbody&gt;


&lt;tr valign=&quot;top&quot;&gt;
&lt;td colspan=&quot;2&quot; align=&quot;left&quot;&gt;

        &lt;br&gt;
&lt;/td&gt;&lt;/tr&gt;
&lt;tr valign=&quot;top&quot;&gt;
&lt;td align=&quot;left&quot;&gt;
&lt;h5&gt;Name&lt;/h5&gt;&lt;/td&gt;
&lt;td align=&quot;left&quot;&gt;&lt;input style=&quot;width: 300px; font-family: verdana;&quot; size=&quot;40&quot; name=&quot;name&quot; value=&quot;@@@name@@@&quot;&gt;&lt;/td&gt;&lt;/tr&gt;
&lt;tr valign=&quot;top&quot;&gt;
&lt;td align=&quot;left&quot;&gt;
&lt;h5&gt;Email&lt;/h5&gt;&lt;/td&gt;
&lt;td align=&quot;left&quot;&gt;&lt;input style=&quot;width: 300px; font-family: verdana;&quot; size=&quot;40&quot; name=&quot;email&quot; value=&quot;@@@email@@@&quot;&gt;&lt;/td&gt;&lt;/tr&gt;
&lt;tr valign=&quot;top&quot;&gt;
&lt;td align=&quot;left&quot;&gt;
&lt;h5&gt;Username&lt;/h5&gt;&lt;/td&gt;
&lt;td align=&quot;left&quot;&gt;&lt;input style=&quot;width: 300px; font-family: verdana;&quot; size=&quot;40&quot; name=&quot;username&quot; value=&quot;@@@username@@@&quot;&gt;&lt;/td&gt;&lt;/tr&gt;
&lt;tr valign=&quot;top&quot;&gt;
&lt;td align=&quot;left&quot;&gt;
&lt;h5&gt;Password&lt;/h5&gt;&lt;/td&gt;
&lt;td align=&quot;left&quot;&gt;&lt;input style=&quot;width: 300px; font-family: verdana;&quot; size=&quot;40&quot; name=&quot;password&quot; value=&quot;@@@password@@@&quot;&gt;&lt;/td&gt;&lt;/tr&gt;
&lt;tr valign=&quot;top&quot;&gt;
&lt;td colspan=&quot;2&quot; align=&quot;middle&quot;&gt;&amp;nbsp; 
&lt;div&gt;&lt;input class=&quot;buttonbox&quot; value=&quot;Send&quot; type=&quot;submit&quot;&gt;&lt;/div&gt;&lt;/td&gt;&lt;/tr&gt;
&lt;tr&gt;
&lt;td&gt;&amp;nbsp;&lt;/td&gt;
&lt;td&gt;&amp;nbsp;&lt;/td&gt;&lt;/tr&gt;&lt;/tbody&gt;&lt;/table&gt;&lt;/form&gt;&lt;p&gt;&lt;/p&gt;&lt;/div&gt;
&lt;p&gt;&amp;nbsp;&lt;/p&gt;
&lt;p&gt;&amp;nbsp;&lt;/p&gt;" />
   <column name="template" value="" />
   <column name="stylesheet" value="" />
   <column name="contentclass" value="page" />
   <column name="contenttype" value="Forms" />
   <column name="contentgroup" value="User Registration" />
   <column name="users_type" value="" />
   <column name="users_group" value="" />
   <column name="developers_type" value="" />
   <column name="developers_group" value="" />
   <column name="creators_type" value="" />
   <column name="creators_group" value="" />
   <column name="editors_type" value="" />
   <column name="editors_group" value="" />
   <column name="publishers_type" value="" />
   <column name="publishers_group" value="" />
   <column name="administrators_type" value="" />
   <column name="administrators_group" value="" />
   <column name="checkedout" value="" />
   <column name="page_top" value="0" />
   <column name="page_up" value="0" />
   <column name="page_next" value="0" />
   <column name="page_previous" value="0" />
   <column name="page_first" value="0" />
   <column name="page_last" value="0" />
   <column name="upload_filename" value="" />
   <column name="server_filename" value="" />
   <column name="product_code" value="" />
   <column name="product_currency" value="" />
   <column name="product_price" value="" />
   <column name="product_stock" value="" />
   <column name="product_comment" value="" />
   <column name="product_email" value="" />
   <column name="product_url" value="" />
   <column name="searchable" value="" />
  </row>
  <row>
   <column name="id" value="6640" />
   <column name="locked" value="0" />
   <column name="created" value="2004-06-19 15:52:32" />
   <column name="updated" value="2004-07-18 17:21:30" />
   <column name="published" value="2004-07-18 17:21:30" />
   <column name="scheduled_publish" value="" />
   <column name="scheduled_unpublish" value="" />
   <column name="status" value="" />
   <column name="created_by" value="admin" />
   <column name="updated_by" value="admin" />
   <column name="published_by" value="admin" />
   <column name="revision" value="" />
   <column name="version" value="" />
   <column name="version_master" value="0" />
   <column name="title" value="Personal Page Template" />
   <column name="author" value="" />
   <column name="keywords" value="" />
   <column name="description" value="" />
   <column name="htmlheader" value="" />
   <column name="htmlbodyonload" value="" />
   <column name="url" value="" />
   <column name="content" value="@@@name@@@'s personal page&lt;br&gt;
&lt;br&gt;" />
   <column name="template" value="" />
   <column name="stylesheet" value="" />
   <column name="contentclass" value="page" />
   <column name="contenttype" value="General" />
   <column name="contentgroup" value="Personal Pages" />
   <column name="users_type" value="" />
   <column name="users_group" value="" />
   <column name="developers_type" value="" />
   <column name="developers_group" value="" />
   <column name="creators_type" value="0" />
   <column name="creators_group" value="0" />
   <column name="editors_type" value="" />
   <column name="editors_group" value="" />
   <column name="publishers_type" value="0" />
   <column name="publishers_group" value="0" />
   <column name="administrators_type" value="" />
   <column name="administrators_group" value="" />
   <column name="checkedout" value="" />
   <column name="page_top" value="0" />
   <column name="page_up" value="0" />
   <column name="page_next" value="0" />
   <column name="page_previous" value="0" />
   <column name="page_first" value="0" />
   <column name="page_last" value="0" />
   <column name="upload_filename" value="" />
   <column name="server_filename" value="" />
   <column name="product_code" value="" />
   <column name="product_currency" value="" />
   <column name="product_price" value="" />
   <column name="product_stock" value="" />
   <column name="product_comment" value="" />
   <column name="product_email" value="" />
   <column name="product_url" value="" />
   <column name="searchable" value="" />
  </row>
  <row>
   <column name="id" value="6641" />
   <column name="locked" value="0" />
   <column name="created" value="2004-06-19 16:54:01" />
   <column name="updated" value="2004-07-07 16:07:18" />
   <column name="published" value="2004-07-07 16:07:18" />
   <column name="scheduled_publish" value="" />
   <column name="scheduled_unpublish" value="" />
   <column name="status" value="" />
   <column name="created_by" value="admin" />
   <column name="updated_by" value="admin" />
   <column name="published_by" value="admin" />
   <column name="revision" value="" />
   <column name="version" value="" />
   <column name="version_master" value="0" />
   <column name="title" value="User Registration Completed" />
   <column name="author" value="" />
   <column name="keywords" value="" />
   <column name="description" value="" />
   <column name="htmlheader" value="" />
   <column name="htmlbodyonload" value="" />
   <column name="url" value="" />
   <column name="content" value="&lt;div class=&quot;box&quot;&gt;
&lt;h2&gt;Thank You&lt;/h2&gt;
&lt;p&gt;&amp;nbsp;&lt;/p&gt;
&lt;p&gt;Thank you for signing up for a user account. Your user account details will be emailed to you.&lt;/p&gt;
&lt;/div&gt;" />
   <column name="template" value="" />
   <column name="stylesheet" value="" />
   <column name="contentclass" value="page" />
   <column name="contenttype" value="Special" />
   <column name="contentgroup" value="User Registration" />
   <column name="users_type" value="" />
   <column name="users_group" value="" />
   <column name="developers_type" value="" />
   <column name="developers_group" value="" />
   <column name="creators_type" value="" />
   <column name="creators_group" value="" />
   <column name="editors_type" value="" />
   <column name="editors_group" value="" />
   <column name="publishers_type" value="" />
   <column name="publishers_group" value="" />
   <column name="administrators_type" value="" />
   <column name="administrators_group" value="" />
   <column name="checkedout" value="" />
   <column name="page_top" value="0" />
   <column name="page_up" value="0" />
   <column name="page_next" value="0" />
   <column name="page_previous" value="0" />
   <column name="page_first" value="0" />
   <column name="page_last" value="0" />
   <column name="upload_filename" value="" />
   <column name="server_filename" value="" />
   <column name="product_code" value="" />
   <column name="product_currency" value="" />
   <column name="product_price" value="" />
   <column name="product_stock" value="" />
   <column name="product_comment" value="" />
   <column name="product_email" value="" />
   <column name="product_url" value="" />
   <column name="searchable" value="" />
  </row>
  <row>
   <column name="id" value="6646" />
   <column name="locked" value="0" />
   <column name="created" value="2004-07-02 08:59:55" />
   <column name="updated" value="2004-07-07 16:08:08" />
   <column name="published" value="2004-07-07 16:08:08" />
   <column name="scheduled_publish" value="" />
   <column name="scheduled_unpublish" value="" />
   <column name="status" value="" />
   <column name="created_by" value="admin" />
   <column name="updated_by" value="admin" />
   <column name="published_by" value="admin" />
   <column name="revision" value="" />
   <column name="version" value="" />
   <column name="version_master" value="0" />
   <column name="title" value="User Registration Confirmation" />
   <column name="author" value="" />
   <column name="keywords" value="" />
   <column name="description" value="" />
   <column name="htmlheader" value="" />
   <column name="htmlbodyonload" value="" />
   <column name="url" value="" />
   <column name="content" value="&lt;div class=&quot;box&quot;&gt;
&lt;h2&gt;&amp;nbsp;&lt;/h2&gt;
&lt;h2&gt;Thank You&lt;/h2&gt;
&lt;p&gt;&amp;nbsp;&lt;/p&gt;
&lt;p&gt;Thank you for signing up for a user account. Your user account details are:&lt;br&gt;
&lt;/p&gt;
&lt;p&gt;&lt;br&gt;
&lt;/p&gt;
&lt;p&gt;&amp;nbsp;&amp;nbsp;&amp;nbsp; Name: @@@name@@@&lt;/p&gt;
&lt;p&gt;&amp;nbsp;&amp;nbsp;&amp;nbsp; Email: @@@email@@@&lt;br&gt;
&amp;nbsp;&amp;nbsp;&amp;nbsp; Username: @@@username@@@&lt;br&gt;
&amp;nbsp;&amp;nbsp;&amp;nbsp; Password: @@@password@@@&lt;br&gt;
&lt;/p&gt;
&lt;p&gt;&lt;br&gt;
&lt;/p&gt;
&lt;p&gt;&amp;nbsp;&amp;nbsp;&amp;nbsp; Personal page:&lt;br&gt;
&amp;nbsp;&amp;nbsp;&amp;nbsp; &lt;a href=&quot;@@@personalpage@@@&quot;&gt;@@@personalpage@@@&lt;/a&gt;&lt;br&gt;
&lt;/p&gt;
&lt;p&gt;&lt;br&gt;
&amp;nbsp;&amp;nbsp;&amp;nbsp; Personal details and page administration:&lt;br&gt;
&amp;nbsp;&amp;nbsp;&amp;nbsp; &lt;a href=&quot;@@@personaladmin@@@&quot;&gt;@@@personaladmin@@@&lt;/a&gt;&lt;br&gt;
&lt;/p&gt;
&amp;nbsp;&lt;p&gt;&lt;/p&gt;&lt;/div&gt;" />
   <column name="template" value="" />
   <column name="stylesheet" value="" />
   <column name="contentclass" value="page" />
   <column name="contenttype" value="Emails" />
   <column name="contentgroup" value="User Registration" />
   <column name="users_type" value="" />
   <column name="users_group" value="" />
   <column name="developers_type" value="" />
   <column name="developers_group" value="" />
   <column name="creators_type" value="" />
   <column name="creators_group" value="" />
   <column name="editors_type" value="" />
   <column name="editors_group" value="" />
   <column name="publishers_type" value="" />
   <column name="publishers_group" value="" />
   <column name="administrators_type" value="" />
   <column name="administrators_group" value="" />
   <column name="checkedout" value="" />
   <column name="page_top" value="0" />
   <column name="page_up" value="0" />
   <column name="page_next" value="0" />
   <column name="page_previous" value="0" />
   <column name="page_first" value="0" />
   <column name="page_last" value="0" />
   <column name="upload_filename" value="" />
   <column name="server_filename" value="" />
   <column name="product_code" value="" />
   <column name="product_currency" value="" />
   <column name="product_price" value="" />
   <column name="product_stock" value="" />
   <column name="product_comment" value="" />
   <column name="product_email" value="" />
   <column name="product_url" value="" />
   <column name="searchable" value="" />
  </row>
  <row>
   <column name="id" value="6647" />
   <column name="locked" value="0" />
   <column name="created" value="2004-07-02 09:02:20" />
   <column name="updated" value="2004-07-07 16:08:42" />
   <column name="published" value="2004-07-07 16:08:42" />
   <column name="scheduled_publish" value="" />
   <column name="scheduled_unpublish" value="" />
   <column name="status" value="" />
   <column name="created_by" value="admin" />
   <column name="updated_by" value="admin" />
   <column name="published_by" value="admin" />
   <column name="revision" value="" />
   <column name="version" value="" />
   <column name="version_master" value="0" />
   <column name="title" value="User Registration Notification:" />
   <column name="author" value="" />
   <column name="keywords" value="" />
   <column name="description" value="" />
   <column name="htmlheader" value="" />
   <column name="htmlbodyonload" value="" />
   <column name="url" value="" />
   <column name="content" value="&lt;p&gt;A new user has registered with the following details:&lt;br&gt;
&lt;br&gt;
&amp;nbsp;&amp;nbsp;&amp;nbsp; Name: @@@name@@@&lt;br&gt;
&amp;nbsp;&amp;nbsp;&amp;nbsp; Email: @@@email@@@&lt;br&gt;
&amp;nbsp;&amp;nbsp;&amp;nbsp; Username: @@@username@@@&lt;br&gt;
&amp;nbsp;&amp;nbsp;&amp;nbsp; Password: @@@password@@@&lt;br&gt;
&lt;br&gt;
&amp;nbsp;&amp;nbsp;&amp;nbsp; Personal page:&lt;br&gt;
&amp;nbsp;&amp;nbsp;&amp;nbsp; &lt;a href=&quot;@@@personalpage@@@&quot;&gt;@@@personalpage@@@&lt;/a&gt;&lt;br&gt;
&lt;/p&gt;" />
   <column name="template" value="" />
   <column name="stylesheet" value="" />
   <column name="contentclass" value="page" />
   <column name="contenttype" value="Emails" />
   <column name="contentgroup" value="User Registration" />
   <column name="users_type" value="" />
   <column name="users_group" value="" />
   <column name="developers_type" value="" />
   <column name="developers_group" value="" />
   <column name="creators_type" value="" />
   <column name="creators_group" value="" />
   <column name="editors_type" value="" />
   <column name="editors_group" value="" />
   <column name="publishers_type" value="" />
   <column name="publishers_group" value="" />
   <column name="administrators_type" value="" />
   <column name="administrators_group" value="" />
   <column name="checkedout" value="" />
   <column name="page_top" value="0" />
   <column name="page_up" value="0" />
   <column name="page_next" value="0" />
   <column name="page_previous" value="0" />
   <column name="page_first" value="0" />
   <column name="page_last" value="0" />
   <column name="upload_filename" value="" />
   <column name="server_filename" value="" />
   <column name="product_code" value="" />
   <column name="product_currency" value="" />
   <column name="product_price" value="" />
   <column name="product_stock" value="" />
   <column name="product_comment" value="" />
   <column name="product_email" value="" />
   <column name="product_url" value="" />
   <column name="searchable" value="" />
  </row>
 </table>
 <table name="content_elements">
  <row>
   <column name="content_id" value="6639" />
   <column name="element" value="banner" />
   <column name="element_id" value="-1" />
  </row>
  <row>
   <column name="content_id" value="6639" />
   <column name="element" value="logo" />
   <column name="element_id" value="-1" />
  </row>
  <row>
   <column name="content_id" value="6639" />
   <column name="element" value="menu" />
   <column name="element_id" value="-1" />
  </row>
  <row>
   <column name="content_id" value="6639" />
   <column name="element" value="news" />
   <column name="element_id" value="-1" />
  </row>
  <row>
   <column name="content_id" value="6639" />
   <column name="element" value="offer" />
   <column name="element_id" value="-1" />
  </row>
  <row>
   <column name="content_id" value="6639" />
   <column name="element" value="randompicture" />
   <column name="element_id" value="-1" />
  </row>
  <row>
   <column name="content_id" value="6639" />
   <column name="element" value="rndoffer" />
   <column name="element_id" value="-1" />
  </row>
  <row>
   <column name="content_id" value="6639" />
   <column name="element" value="toolbar" />
   <column name="element_id" value="-1" />
  </row>
  <row>
   <column name="content_id" value="6640" />
   <column name="element" value="banner" />
   <column name="element_id" value="-1" />
  </row>
  <row>
   <column name="content_id" value="6640" />
   <column name="element" value="logo" />
   <column name="element_id" value="-1" />
  </row>
  <row>
   <column name="content_id" value="6640" />
   <column name="element" value="menu" />
   <column name="element_id" value="-1" />
  </row>
  <row>
   <column name="content_id" value="6640" />
   <column name="element" value="news" />
   <column name="element_id" value="-1" />
  </row>
  <row>
   <column name="content_id" value="6640" />
   <column name="element" value="offer" />
   <column name="element_id" value="-1" />
  </row>
  <row>
   <column name="content_id" value="6640" />
   <column name="element" value="randompicture" />
   <column name="element_id" value="-1" />
  </row>
  <row>
   <column name="content_id" value="6640" />
   <column name="element" value="rndoffer" />
   <column name="element_id" value="-1" />
  </row>
  <row>
   <column name="content_id" value="6640" />
   <column name="element" value="toolbar" />
   <column name="element_id" value="-1" />
  </row>
  <row>
   <column name="content_id" value="6641" />
   <column name="element" value="banner" />
   <column name="element_id" value="-1" />
  </row>
  <row>
   <column name="content_id" value="6641" />
   <column name="element" value="logo" />
   <column name="element_id" value="-1" />
  </row>
  <row>
   <column name="content_id" value="6641" />
   <column name="element" value="menu" />
   <column name="element_id" value="-1" />
  </row>
  <row>
   <column name="content_id" value="6641" />
   <column name="element" value="news" />
   <column name="element_id" value="-1" />
  </row>
  <row>
   <column name="content_id" value="6641" />
   <column name="element" value="offer" />
   <column name="element_id" value="-1" />
  </row>
  <row>
   <column name="content_id" value="6641" />
   <column name="element" value="randompicture" />
   <column name="element_id" value="-1" />
  </row>
  <row>
   <column name="content_id" value="6641" />
   <column name="element" value="rndoffer" />
   <column name="element_id" value="-1" />
  </row>
  <row>
   <column name="content_id" value="6641" />
   <column name="element" value="toolbar" />
   <column name="element_id" value="-1" />
  </row>
  <row>
   <column name="content_id" value="6646" />
   <column name="element" value="banner" />
   <column name="element_id" value="-1" />
  </row>
  <row>
   <column name="content_id" value="6646" />
   <column name="element" value="logo" />
   <column name="element_id" value="-1" />
  </row>
  <row>
   <column name="content_id" value="6646" />
   <column name="element" value="menu" />
   <column name="element_id" value="-1" />
  </row>
  <row>
   <column name="content_id" value="6646" />
   <column name="element" value="news" />
   <column name="element_id" value="-1" />
  </row>
  <row>
   <column name="content_id" value="6646" />
   <column name="element" value="offer" />
   <column name="element_id" value="-1" />
  </row>
  <row>
   <column name="content_id" value="6646" />
   <column name="element" value="randompicture" />
   <column name="element_id" value="-1" />
  </row>
  <row>
   <column name="content_id" value="6646" />
   <column name="element" value="rndoffer" />
   <column name="element_id" value="-1" />
  </row>
  <row>
   <column name="content_id" value="6646" />
   <column name="element" value="toolbar" />
   <column name="element_id" value="-1" />
  </row>
  <row>
   <column name="content_id" value="6647" />
   <column name="element" value="banner" />
   <column name="element_id" value="-1" />
  </row>
  <row>
   <column name="content_id" value="6647" />
   <column name="element" value="logo" />
   <column name="element_id" value="-1" />
  </row>
  <row>
   <column name="content_id" value="6647" />
   <column name="element" value="menu" />
   <column name="element_id" value="-1" />
  </row>
  <row>
   <column name="content_id" value="6647" />
   <column name="element" value="news" />
   <column name="element_id" value="-1" />
  </row>
  <row>
   <column name="content_id" value="6647" />
   <column name="element" value="offer" />
   <column name="element_id" value="-1" />
  </row>
  <row>
   <column name="content_id" value="6647" />
   <column name="element" value="randompicture" />
   <column name="element_id" value="-1" />
  </row>
  <row>
   <column name="content_id" value="6647" />
   <column name="element" value="rndoffer" />
   <column name="element_id" value="-1" />
  </row>
  <row>
   <column name="content_id" value="6647" />
   <column name="element" value="toolbar" />
   <column name="element_id" value="-1" />
  </row>
 </table>
 <table name="content_public">
  <row>
   <column name="id" value="6639" />
   <column name="locked" value="0" />
   <column name="created" value="2004-06-18 01:02:23" />
   <column name="updated" value="2004-06-19 16:55:23" />
   <column name="published" value="2004-06-19 16:55:23" />
   <column name="scheduled_publish" value="" />
   <column name="scheduled_unpublish" value="" />
   <column name="status" value="" />
   <column name="created_by" value="admin" />
   <column name="updated_by" value="admin" />
   <column name="published_by" value="admin" />
   <column name="revision" value="" />
   <column name="version" value="" />
   <column name="version_master" value="0" />
   <column name="title" value="User Registration Form" />
   <column name="author" value="" />
   <column name="keywords" value="" />
   <column name="description" value="" />
   <column name="htmlheader" value="" />
   <column name="htmlbodyonload" value="" />
   <column name="url" value="" />
   <column name="content" value="&lt;div class=&quot;box&quot;&gt;
&lt;h2&gt;&amp;nbsp;&lt;/h2&gt;
&lt;h2&gt;Sign Up For User Account&lt;br&gt;
&lt;/h2&gt;
&lt;p&gt;&amp;nbsp;&lt;/p&gt;
&lt;p&gt;&lt;font color=&quot;red&quot;&gt;&lt;b&gt;@@@error@@@&lt;/b&gt;&lt;/font&gt;&lt;/p&gt;
&lt;form action=&quot;/register.php?id=@@@id@@@&quot; method=&quot;post&quot;&gt;
&lt;input name=&quot;user_id&quot; value=&quot;573&quot; type=&quot;hidden&quot;&gt;
&lt;input name=&quot;content_id&quot; value=&quot;6640&quot; type=&quot;hidden&quot;&gt;
&lt;input name=&quot;publish&quot; value=&quot;yes&quot; type=&quot;hidden&quot;&gt;
&lt;input name=&quot;redirect&quot; value=&quot;/page.php?id=6641&quot; type=&quot;hidden&quot;&gt;
&lt;table align=&quot;center&quot; border=&quot;0&quot; cellpadding=&quot;0&quot; cellspacing=&quot;0&quot; width=&quot;400&quot;&gt;
&lt;tbody&gt;


&lt;tr valign=&quot;top&quot;&gt;
&lt;td colspan=&quot;2&quot; align=&quot;left&quot;&gt;

        &lt;br&gt;
&lt;/td&gt;&lt;/tr&gt;
&lt;tr valign=&quot;top&quot;&gt;
&lt;td align=&quot;left&quot;&gt;
&lt;h5&gt;Name&lt;/h5&gt;&lt;/td&gt;
&lt;td align=&quot;left&quot;&gt;&lt;input style=&quot;width: 300px; font-family: verdana;&quot; size=&quot;40&quot; name=&quot;name&quot; value=&quot;@@@name@@@&quot;&gt;&lt;/td&gt;&lt;/tr&gt;
&lt;tr valign=&quot;top&quot;&gt;
&lt;td align=&quot;left&quot;&gt;
&lt;h5&gt;Email&lt;/h5&gt;&lt;/td&gt;
&lt;td align=&quot;left&quot;&gt;&lt;input style=&quot;width: 300px; font-family: verdana;&quot; size=&quot;40&quot; name=&quot;email&quot; value=&quot;@@@email@@@&quot;&gt;&lt;/td&gt;&lt;/tr&gt;
&lt;tr valign=&quot;top&quot;&gt;
&lt;td align=&quot;left&quot;&gt;
&lt;h5&gt;Username&lt;/h5&gt;&lt;/td&gt;
&lt;td align=&quot;left&quot;&gt;&lt;input style=&quot;width: 300px; font-family: verdana;&quot; size=&quot;40&quot; name=&quot;username&quot; value=&quot;@@@username@@@&quot;&gt;&lt;/td&gt;&lt;/tr&gt;
&lt;tr valign=&quot;top&quot;&gt;
&lt;td align=&quot;left&quot;&gt;
&lt;h5&gt;Password&lt;/h5&gt;&lt;/td&gt;
&lt;td align=&quot;left&quot;&gt;&lt;input style=&quot;width: 300px; font-family: verdana;&quot; size=&quot;40&quot; name=&quot;password&quot; value=&quot;@@@password@@@&quot;&gt;&lt;/td&gt;&lt;/tr&gt;
&lt;tr valign=&quot;top&quot;&gt;
&lt;td colspan=&quot;2&quot; align=&quot;middle&quot;&gt;&amp;nbsp; 
&lt;div&gt;&lt;input class=&quot;buttonbox&quot; value=&quot;Send&quot; type=&quot;submit&quot;&gt;&lt;/div&gt;&lt;/td&gt;&lt;/tr&gt;
&lt;tr&gt;
&lt;td&gt;&amp;nbsp;&lt;/td&gt;
&lt;td&gt;&amp;nbsp;&lt;/td&gt;&lt;/tr&gt;&lt;/tbody&gt;&lt;/table&gt;&lt;/form&gt;&lt;p&gt;&lt;/p&gt;&lt;/div&gt;
&lt;p&gt;&amp;nbsp;&lt;/p&gt;
&lt;p&gt;&amp;nbsp;&lt;/p&gt;" />
   <column name="template" value="" />
   <column name="stylesheet" value="" />
   <column name="contentclass" value="page" />
   <column name="contenttype" value="Forms" />
   <column name="contentgroup" value="User Registration" />
   <column name="users_type" value="" />
   <column name="users_group" value="" />
   <column name="developers_type" value="" />
   <column name="developers_group" value="" />
   <column name="creators_type" value="" />
   <column name="creators_group" value="" />
   <column name="editors_type" value="" />
   <column name="editors_group" value="" />
   <column name="publishers_type" value="" />
   <column name="publishers_group" value="" />
   <column name="administrators_type" value="" />
   <column name="administrators_group" value="" />
   <column name="checkedout" value="" />
   <column name="page_top" value="0" />
   <column name="page_up" value="0" />
   <column name="page_next" value="0" />
   <column name="page_previous" value="0" />
   <column name="page_first" value="0" />
   <column name="page_last" value="0" />
   <column name="upload_filename" value="" />
   <column name="server_filename" value="" />
   <column name="product_code" value="" />
   <column name="product_currency" value="" />
   <column name="product_price" value="" />
   <column name="product_stock" value="" />
   <column name="product_comment" value="" />
   <column name="product_email" value="" />
   <column name="product_url" value="" />
   <column name="searchable" value="" />
  </row>
  <row>
   <column name="id" value="6640" />
   <column name="locked" value="0" />
   <column name="created" value="2004-06-19 15:52:32" />
   <column name="updated" value="2004-07-18 17:21:30" />
   <column name="published" value="2004-07-18 17:21:30" />
   <column name="scheduled_publish" value="" />
   <column name="scheduled_unpublish" value="" />
   <column name="status" value="" />
   <column name="created_by" value="admin" />
   <column name="updated_by" value="admin" />
   <column name="published_by" value="admin" />
   <column name="revision" value="" />
   <column name="version" value="" />
   <column name="version_master" value="0" />
   <column name="title" value="Personal Page Template" />
   <column name="author" value="" />
   <column name="keywords" value="" />
   <column name="description" value="" />
   <column name="htmlheader" value="" />
   <column name="htmlbodyonload" value="" />
   <column name="url" value="" />
   <column name="content" value="@@@name@@@'s personal page&lt;br&gt;
&lt;br&gt;" />
   <column name="template" value="" />
   <column name="stylesheet" value="" />
   <column name="contentclass" value="page" />
   <column name="contenttype" value="General" />
   <column name="contentgroup" value="Personal Pages" />
   <column name="users_type" value="" />
   <column name="users_group" value="" />
   <column name="developers_type" value="" />
   <column name="developers_group" value="" />
   <column name="creators_type" value="0" />
   <column name="creators_group" value="0" />
   <column name="editors_type" value="" />
   <column name="editors_group" value="" />
   <column name="publishers_type" value="0" />
   <column name="publishers_group" value="0" />
   <column name="administrators_type" value="" />
   <column name="administrators_group" value="" />
   <column name="checkedout" value="" />
   <column name="page_top" value="0" />
   <column name="page_up" value="0" />
   <column name="page_next" value="0" />
   <column name="page_previous" value="0" />
   <column name="page_first" value="0" />
   <column name="page_last" value="0" />
   <column name="upload_filename" value="" />
   <column name="server_filename" value="" />
   <column name="product_code" value="" />
   <column name="product_currency" value="" />
   <column name="product_price" value="" />
   <column name="product_stock" value="" />
   <column name="product_comment" value="" />
   <column name="product_email" value="" />
   <column name="product_url" value="" />
   <column name="searchable" value="" />
  </row>
  <row>
   <column name="id" value="6641" />
   <column name="locked" value="0" />
   <column name="created" value="2004-06-19 16:54:01" />
   <column name="updated" value="2004-07-07 16:07:18" />
   <column name="published" value="2004-07-07 16:07:18" />
   <column name="scheduled_publish" value="" />
   <column name="scheduled_unpublish" value="" />
   <column name="status" value="" />
   <column name="created_by" value="admin" />
   <column name="updated_by" value="admin" />
   <column name="published_by" value="admin" />
   <column name="revision" value="" />
   <column name="version" value="" />
   <column name="version_master" value="0" />
   <column name="title" value="User Registration Completed" />
   <column name="author" value="" />
   <column name="keywords" value="" />
   <column name="description" value="" />
   <column name="htmlheader" value="" />
   <column name="htmlbodyonload" value="" />
   <column name="url" value="" />
   <column name="content" value="&lt;div class=&quot;box&quot;&gt;
&lt;h2&gt;Thank You&lt;/h2&gt;
&lt;p&gt;&amp;nbsp;&lt;/p&gt;
&lt;p&gt;Thank you for signing up for a user account. Your user account details will be emailed to you.&lt;/p&gt;
&lt;/div&gt;" />
   <column name="template" value="" />
   <column name="stylesheet" value="" />
   <column name="contentclass" value="page" />
   <column name="contenttype" value="Special" />
   <column name="contentgroup" value="User Registration" />
   <column name="users_type" value="" />
   <column name="users_group" value="" />
   <column name="developers_type" value="" />
   <column name="developers_group" value="" />
   <column name="creators_type" value="" />
   <column name="creators_group" value="" />
   <column name="editors_type" value="" />
   <column name="editors_group" value="" />
   <column name="publishers_type" value="" />
   <column name="publishers_group" value="" />
   <column name="administrators_type" value="" />
   <column name="administrators_group" value="" />
   <column name="checkedout" value="" />
   <column name="page_top" value="0" />
   <column name="page_up" value="0" />
   <column name="page_next" value="0" />
   <column name="page_previous" value="0" />
   <column name="page_first" value="0" />
   <column name="page_last" value="0" />
   <column name="upload_filename" value="" />
   <column name="server_filename" value="" />
   <column name="product_code" value="" />
   <column name="product_currency" value="" />
   <column name="product_price" value="" />
   <column name="product_stock" value="" />
   <column name="product_comment" value="" />
   <column name="product_email" value="" />
   <column name="product_url" value="" />
   <column name="searchable" value="" />
  </row>
  <row>
   <column name="id" value="6646" />
   <column name="locked" value="0" />
   <column name="created" value="2004-07-02 08:59:55" />
   <column name="updated" value="2004-07-07 16:08:08" />
   <column name="published" value="2004-07-07 16:08:08" />
   <column name="scheduled_publish" value="" />
   <column name="scheduled_unpublish" value="" />
   <column name="status" value="" />
   <column name="created_by" value="admin" />
   <column name="updated_by" value="admin" />
   <column name="published_by" value="admin" />
   <column name="revision" value="" />
   <column name="version" value="" />
   <column name="version_master" value="0" />
   <column name="title" value="User Registration Confirmation" />
   <column name="author" value="" />
   <column name="keywords" value="" />
   <column name="description" value="" />
   <column name="htmlheader" value="" />
   <column name="htmlbodyonload" value="" />
   <column name="url" value="" />
   <column name="content" value="&lt;div class=&quot;box&quot;&gt;
&lt;h2&gt;&amp;nbsp;&lt;/h2&gt;
&lt;h2&gt;Thank You&lt;/h2&gt;
&lt;p&gt;&amp;nbsp;&lt;/p&gt;
&lt;p&gt;Thank you for signing up for a user account. Your user account details are:&lt;br&gt;
&lt;/p&gt;
&lt;p&gt;&lt;br&gt;
&lt;/p&gt;
&lt;p&gt;&amp;nbsp;&amp;nbsp;&amp;nbsp; Name: @@@name@@@&lt;/p&gt;
&lt;p&gt;&amp;nbsp;&amp;nbsp;&amp;nbsp; Email: @@@email@@@&lt;br&gt;
&amp;nbsp;&amp;nbsp;&amp;nbsp; Username: @@@username@@@&lt;br&gt;
&amp;nbsp;&amp;nbsp;&amp;nbsp; Password: @@@password@@@&lt;br&gt;
&lt;/p&gt;
&lt;p&gt;&lt;br&gt;
&lt;/p&gt;
&lt;p&gt;&amp;nbsp;&amp;nbsp;&amp;nbsp; Personal page:&lt;br&gt;
&amp;nbsp;&amp;nbsp;&amp;nbsp; &lt;a href=&quot;@@@personalpage@@@&quot;&gt;@@@personalpage@@@&lt;/a&gt;&lt;br&gt;
&lt;/p&gt;
&lt;p&gt;&lt;br&gt;
&amp;nbsp;&amp;nbsp;&amp;nbsp; Personal details and page administration:&lt;br&gt;
&amp;nbsp;&amp;nbsp;&amp;nbsp; &lt;a href=&quot;@@@personaladmin@@@&quot;&gt;@@@personaladmin@@@&lt;/a&gt;&lt;br&gt;
&lt;/p&gt;
&amp;nbsp;&lt;p&gt;&lt;/p&gt;&lt;/div&gt;" />
   <column name="template" value="" />
   <column name="stylesheet" value="" />
   <column name="contentclass" value="page" />
   <column name="contenttype" value="Emails" />
   <column name="contentgroup" value="User Registration" />
   <column name="users_type" value="" />
   <column name="users_group" value="" />
   <column name="developers_type" value="" />
   <column name="developers_group" value="" />
   <column name="creators_type" value="" />
   <column name="creators_group" value="" />
   <column name="editors_type" value="" />
   <column name="editors_group" value="" />
   <column name="publishers_type" value="" />
   <column name="publishers_group" value="" />
   <column name="administrators_type" value="" />
   <column name="administrators_group" value="" />
   <column name="checkedout" value="" />
   <column name="page_top" value="0" />
   <column name="page_up" value="0" />
   <column name="page_next" value="0" />
   <column name="page_previous" value="0" />
   <column name="page_first" value="0" />
   <column name="page_last" value="0" />
   <column name="upload_filename" value="" />
   <column name="server_filename" value="" />
   <column name="product_code" value="" />
   <column name="product_currency" value="" />
   <column name="product_price" value="" />
   <column name="product_stock" value="" />
   <column name="product_comment" value="" />
   <column name="product_email" value="" />
   <column name="product_url" value="" />
   <column name="searchable" value="" />
  </row>
  <row>
   <column name="id" value="6647" />
   <column name="locked" value="0" />
   <column name="created" value="2004-07-02 09:02:20" />
   <column name="updated" value="2004-07-07 16:08:42" />
   <column name="published" value="2004-07-07 16:08:42" />
   <column name="scheduled_publish" value="" />
   <column name="scheduled_unpublish" value="" />
   <column name="status" value="" />
   <column name="created_by" value="admin" />
   <column name="updated_by" value="admin" />
   <column name="published_by" value="admin" />
   <column name="revision" value="" />
   <column name="version" value="" />
   <column name="version_master" value="0" />
   <column name="title" value="User Registration Notification:" />
   <column name="author" value="" />
   <column name="keywords" value="" />
   <column name="description" value="" />
   <column name="htmlheader" value="" />
   <column name="htmlbodyonload" value="" />
   <column name="url" value="" />
   <column name="content" value="&lt;p&gt;A new user has registered with the following details:&lt;br&gt;
&lt;br&gt;
&amp;nbsp;&amp;nbsp;&amp;nbsp; Name: @@@name@@@&lt;br&gt;
&amp;nbsp;&amp;nbsp;&amp;nbsp; Email: @@@email@@@&lt;br&gt;
&amp;nbsp;&amp;nbsp;&amp;nbsp; Username: @@@username@@@&lt;br&gt;
&amp;nbsp;&amp;nbsp;&amp;nbsp; Password: @@@password@@@&lt;br&gt;
&lt;br&gt;
&amp;nbsp;&amp;nbsp;&amp;nbsp; Personal page:&lt;br&gt;
&amp;nbsp;&amp;nbsp;&amp;nbsp; &lt;a href=&quot;@@@personalpage@@@&quot;&gt;@@@personalpage@@@&lt;/a&gt;&lt;br&gt;
&lt;/p&gt;" />
   <column name="template" value="" />
   <column name="stylesheet" value="" />
   <column name="contentclass" value="page" />
   <column name="contenttype" value="Emails" />
   <column name="contentgroup" value="User Registration" />
   <column name="users_type" value="" />
   <column name="users_group" value="" />
   <column name="developers_type" value="" />
   <column name="developers_group" value="" />
   <column name="creators_type" value="" />
   <column name="creators_group" value="" />
   <column name="editors_type" value="" />
   <column name="editors_group" value="" />
   <column name="publishers_type" value="" />
   <column name="publishers_group" value="" />
   <column name="administrators_type" value="" />
   <column name="administrators_group" value="" />
   <column name="checkedout" value="" />
   <column name="page_top" value="0" />
   <column name="page_up" value="0" />
   <column name="page_next" value="0" />
   <column name="page_previous" value="0" />
   <column name="page_first" value="0" />
   <column name="page_last" value="0" />
   <column name="upload_filename" value="" />
   <column name="server_filename" value="" />
   <column name="product_code" value="" />
   <column name="product_currency" value="" />
   <column name="product_price" value="" />
   <column name="product_stock" value="" />
   <column name="product_comment" value="" />
   <column name="product_email" value="" />
   <column name="product_url" value="" />
   <column name="searchable" value="" />
  </row>
 </table>
 <table name="content_public_elements">
  <row>
   <column name="content_id" value="6639" />
   <column name="element" value="banner" />
   <column name="element_id" value="-1" />
  </row>
  <row>
   <column name="content_id" value="6639" />
   <column name="element" value="logo" />
   <column name="element_id" value="-1" />
  </row>
  <row>
   <column name="content_id" value="6639" />
   <column name="element" value="menu" />
   <column name="element_id" value="-1" />
  </row>
  <row>
   <column name="content_id" value="6639" />
   <column name="element" value="news" />
   <column name="element_id" value="-1" />
  </row>
  <row>
   <column name="content_id" value="6639" />
   <column name="element" value="offer" />
   <column name="element_id" value="-1" />
  </row>
  <row>
   <column name="content_id" value="6639" />
   <column name="element" value="randompicture" />
   <column name="element_id" value="-1" />
  </row>
  <row>
   <column name="content_id" value="6639" />
   <column name="element" value="rndoffer" />
   <column name="element_id" value="-1" />
  </row>
  <row>
   <column name="content_id" value="6639" />
   <column name="element" value="toolbar" />
   <column name="element_id" value="-1" />
  </row>
  <row>
   <column name="content_id" value="6640" />
   <column name="element" value="banner" />
   <column name="element_id" value="-1" />
  </row>
  <row>
   <column name="content_id" value="6640" />
   <column name="element" value="logo" />
   <column name="element_id" value="-1" />
  </row>
  <row>
   <column name="content_id" value="6640" />
   <column name="element" value="menu" />
   <column name="element_id" value="-1" />
  </row>
  <row>
   <column name="content_id" value="6640" />
   <column name="element" value="news" />
   <column name="element_id" value="-1" />
  </row>
  <row>
   <column name="content_id" value="6640" />
   <column name="element" value="offer" />
   <column name="element_id" value="-1" />
  </row>
  <row>
   <column name="content_id" value="6640" />
   <column name="element" value="randompicture" />
   <column name="element_id" value="-1" />
  </row>
  <row>
   <column name="content_id" value="6640" />
   <column name="element" value="rndoffer" />
   <column name="element_id" value="-1" />
  </row>
  <row>
   <column name="content_id" value="6640" />
   <column name="element" value="toolbar" />
   <column name="element_id" value="-1" />
  </row>
  <row>
   <column name="content_id" value="6641" />
   <column name="element" value="banner" />
   <column name="element_id" value="-1" />
  </row>
  <row>
   <column name="content_id" value="6641" />
   <column name="element" value="logo" />
   <column name="element_id" value="-1" />
  </row>
  <row>
   <column name="content_id" value="6641" />
   <column name="element" value="menu" />
   <column name="element_id" value="-1" />
  </row>
  <row>
   <column name="content_id" value="6641" />
   <column name="element" value="news" />
   <column name="element_id" value="-1" />
  </row>
  <row>
   <column name="content_id" value="6641" />
   <column name="element" value="offer" />
   <column name="element_id" value="-1" />
  </row>
  <row>
   <column name="content_id" value="6641" />
   <column name="element" value="randompicture" />
   <column name="element_id" value="-1" />
  </row>
  <row>
   <column name="content_id" value="6641" />
   <column name="element" value="rndoffer" />
   <column name="element_id" value="-1" />
  </row>
  <row>
   <column name="content_id" value="6641" />
   <column name="element" value="toolbar" />
   <column name="element_id" value="-1" />
  </row>
  <row>
   <column name="content_id" value="6646" />
   <column name="element" value="banner" />
   <column name="element_id" value="-1" />
  </row>
  <row>
   <column name="content_id" value="6646" />
   <column name="element" value="logo" />
   <column name="element_id" value="-1" />
  </row>
  <row>
   <column name="content_id" value="6646" />
   <column name="element" value="menu" />
   <column name="element_id" value="-1" />
  </row>
  <row>
   <column name="content_id" value="6646" />
   <column name="element" value="news" />
   <column name="element_id" value="-1" />
  </row>
  <row>
   <column name="content_id" value="6646" />
   <column name="element" value="offer" />
   <column name="element_id" value="-1" />
  </row>
  <row>
   <column name="content_id" value="6646" />
   <column name="element" value="randompicture" />
   <column name="element_id" value="-1" />
  </row>
  <row>
   <column name="content_id" value="6646" />
   <column name="element" value="rndoffer" />
   <column name="element_id" value="-1" />
  </row>
  <row>
   <column name="content_id" value="6646" />
   <column name="element" value="toolbar" />
   <column name="element_id" value="-1" />
  </row>
  <row>
   <column name="content_id" value="6647" />
   <column name="element" value="banner" />
   <column name="element_id" value="-1" />
  </row>
  <row>
   <column name="content_id" value="6647" />
   <column name="element" value="logo" />
   <column name="element_id" value="-1" />
  </row>
  <row>
   <column name="content_id" value="6647" />
   <column name="element" value="menu" />
   <column name="element_id" value="-1" />
  </row>
  <row>
   <column name="content_id" value="6647" />
   <column name="element" value="news" />
   <column name="element_id" value="-1" />
  </row>
  <row>
   <column name="content_id" value="6647" />
   <column name="element" value="offer" />
   <column name="element_id" value="-1" />
  </row>
  <row>
   <column name="content_id" value="6647" />
   <column name="element" value="randompicture" />
   <column name="element_id" value="-1" />
  </row>
  <row>
   <column name="content_id" value="6647" />
   <column name="element" value="rndoffer" />
   <column name="element_id" value="-1" />
  </row>
  <row>
   <column name="content_id" value="6647" />
   <column name="element" value="toolbar" />
   <column name="element_id" value="-1" />
  </row>
 </table>
 <table name="contentgroups">
  <row>
   <column name="id" value="252" />
   <column name="contentgroup" value="User Registration" />
   <column name="users_type" value="" />
   <column name="users_group" value="" />
   <column name="developers_type" value="" />
   <column name="developers_group" value="" />
   <column name="creators_type" value="" />
   <column name="creators_group" value="" />
   <column name="editors_type" value="" />
   <column name="editors_group" value="" />
   <column name="publishers_type" value="" />
   <column name="publishers_group" value="" />
   <column name="administrators_type" value="" />
   <column name="administrators_group" value="" />
   <column name="template" value="" />
   <column name="stylesheet" value="" />
  </row>
  <row>
   <column name="id" value="254" />
   <column name="contentgroup" value="Personal Pages" />
   <column name="users_type" value="" />
   <column name="users_group" value="" />
   <column name="developers_type" value="" />
   <column name="developers_group" value="" />
   <column name="creators_type" value="" />
   <column name="creators_group" value="" />
   <column name="editors_type" value="" />
   <column name="editors_group" value="" />
   <column name="publishers_type" value="" />
   <column name="publishers_group" value="" />
   <column name="administrators_type" value="" />
   <column name="administrators_group" value="" />
   <column name="template" value="" />
   <column name="stylesheet" value="" />
  </row>
 </table>
 <table name="users">
  <row>
   <column name="id" value="573" />
   <column name="locked" value="0" />
   <column name="created" value="2004-06-18 02:43:10" />
   <column name="updated" value="2004-06-18 02:50:42" />
   <column name="created_by" value="admin" />
   <column name="updated_by" value="admin" />
   <column name="keywords" value="" />
   <column name="description" value="" />
   <column name="name" value="User Registration" />
   <column name="username" value="userregistration" />
   <column name="password" value="" />
   <column name="email" value="" />
   <column name="userclass" value="" />
   <column name="usertype" value="" />
   <column name="usergroup" value="" />
   <column name="users_type" value="" />
   <column name="users_group" value="" />
   <column name="creators_type" value="0" />
   <column name="creators_group" value="0" />
   <column name="editors_type" value="" />
   <column name="editors_group" value="" />
   <column name="publishers_type" value="0" />
   <column name="publishers_group" value="0" />
   <column name="administrators_type" value="" />
   <column name="administrators_group" value="" />
  </row>
 </table>
 <table name="config">
  <row>
   <column name="configname" value="default_register_confirmation_page" />
   <column name="configvalue" value="6646" />
  </row>
  <row>
   <column name="configname" value="default_register_notification_page" />
   <column name="configvalue" value="6647" />
  </row>
 </table>
</database>
